esri_converter/__init__.py
esri_converter/api.py
esri_converter/exceptions.py
esri_converter/converters/__init__.py
esri_converter/converters/geoparquet_converter.py
esri_converter/utils/__init__.py
esri_converter/utils/formats.py
esri_converter/utils/validation.py
esri_converter-0.1.1.dist-info/METADATA
esri_converter-0.1.1.dist-info/WHEEL
esri_converter-0.1.1.dist-info/licenses/LICENSE
esri_converter-0.1.1.dist-info/RECORD
