Metadata-Version: 2.4
Name: esri-converter
Version: 0.1.1
Summary: Modern tools for converting ESRI proprietary formats to open source formats
Project-URL: Homepage, https://github.com/mihiarc/esri-converter
Project-URL: Documentation, https://esri-converter.readthedocs.io
Project-URL: Repository, https://github.com/mihiarc/esri-converter.git
Project-URL: Issues, https://github.com/mihiarc/esri-converter/issues
Project-URL: Changelog, https://github.com/mihiarc/esri-converter/blob/main/CHANGELOG.md
Author: Chris Mihiar
Maintainer: Chris Mihiar
License: MIT
License-File: LICENSE
Keywords: conversion,esri,gdb,geodatabase,geoparquet,geospatial,gis
Classifier: Development Status :: 4 - Beta
Classifier: Intended Audience :: Developers
Classifier: Intended Audience :: Science/Research
Classifier: License :: OSI Approved :: MIT License
Classifier: Operating System :: OS Independent
Classifier: Programming Language :: Python :: 3
Classifier: Programming Language :: Python :: 3.10
Classifier: Programming Language :: Python :: 3.11
Classifier: Programming Language :: Python :: 3.12
Classifier: Topic :: Scientific/Engineering :: GIS
Classifier: Topic :: Software Development :: Libraries :: Python Modules
Requires-Python: >=3.10
Requires-Dist: fiona>=1.9.0
Requires-Dist: geopandas>=0.14.0
Requires-Dist: polars>=0.20.0
Requires-Dist: psutil>=5.9.0
Requires-Dist: pyarrow>=15.0.0
Requires-Dist: rich>=13.0.0
Requires-Dist: shapely>=2.0.0
Requires-Dist: tqdm>=4.65.0
Provides-Extra: all
Requires-Dist: black>=23.0.0; extra == 'all'
Requires-Dist: build>=0.10.0; extra == 'all'
Requires-Dist: duckdb>=0.10.0; extra == 'all'
Requires-Dist: mkdocs-gen-files>=0.5.0; extra == 'all'
Requires-Dist: mkdocs-literate-nav>=0.6.2; extra == 'all'
Requires-Dist: mkdocs-material>=9.6.14; extra == 'all'
Requires-Dist: mkdocs-mermaid2-plugin>=1.2.1; extra == 'all'
Requires-Dist: mkdocs-section-index>=0.3.10; extra == 'all'
Requires-Dist: mkdocs>=1.6.1; extra == 'all'
Requires-Dist: mkdocstrings[python]>=0.29.1; extra == 'all'
Requires-Dist: mypy>=1.0.0; extra == 'all'
Requires-Dist: pre-commit>=3.0.0; extra == 'all'
Requires-Dist: pytest-cov>=4.0.0; extra == 'all'
Requires-Dist: pytest>=7.0.0; extra == 'all'
Requires-Dist: python-dotenv>=1.0.0; extra == 'all'
Requires-Dist: ruff>=0.1.0; extra == 'all'
Requires-Dist: twine>=4.0.0; extra == 'all'
Provides-Extra: dev
Requires-Dist: black>=23.0.0; extra == 'dev'
Requires-Dist: build>=0.10.0; extra == 'dev'
Requires-Dist: mypy>=1.0.0; extra == 'dev'
Requires-Dist: pre-commit>=3.0.0; extra == 'dev'
Requires-Dist: pytest-cov>=4.0.0; extra == 'dev'
Requires-Dist: pytest>=7.0.0; extra == 'dev'
Requires-Dist: python-dotenv>=1.0.0; extra == 'dev'
Requires-Dist: ruff>=0.1.0; extra == 'dev'
Requires-Dist: twine>=4.0.0; extra == 'dev'
Provides-Extra: docs
Requires-Dist: mkdocs-gen-files>=0.5.0; extra == 'docs'
Requires-Dist: mkdocs-literate-nav>=0.6.2; extra == 'docs'
Requires-Dist: mkdocs-material>=9.6.14; extra == 'docs'
Requires-Dist: mkdocs-mermaid2-plugin>=1.2.1; extra == 'docs'
Requires-Dist: mkdocs-section-index>=0.3.10; extra == 'docs'
Requires-Dist: mkdocs>=1.6.1; extra == 'docs'
Requires-Dist: mkdocstrings[python]>=0.29.1; extra == 'docs'
Provides-Extra: duckdb
Requires-Dist: duckdb>=0.10.0; extra == 'duckdb'
